theta_cloud_client/__init__.py
theta_cloud_client/api/__init__.py
theta_cloud_client/api/default/__init__.py
theta_cloud_client/api/default/create_browser_v1_browsers_post.py
theta_cloud_client/api/default/delete_browser_v1_browsers_sandbox_id_delete.py
theta_cloud_client/api/default/get_browser_v1_browsers_sandbox_id_get.py
theta_cloud_client/api/default/health_health_get.py
theta_cloud_client/api/default/proxy_version_v1_browsers_sid_json_version_get.py
theta_cloud_client/api/default/serve_vnc_v1_browsers_sid_vnc_html_get.py
theta_cloud_client/browser_manager.py
theta_cloud_client/client.py
theta_cloud_client/errors.py
theta_cloud_client/models/__init__.py
theta_cloud_client/models/browser_response.py
theta_cloud_client/models/create_request.py
theta_cloud_client/models/http_validation_error.py
theta_cloud_client/models/validation_error.py
theta_cloud_client/py.typed
theta_cloud_client/types.py
theta_cloud_sdk-0.1.0.dist-info/LICENSE
theta_cloud_sdk-0.1.0.dist-info/METADATA
theta_cloud_sdk-0.1.0.dist-info/WHEEL
theta_cloud_sdk-0.1.0.dist-info/RECORD
