Metadata-Version: 2.3
Name: theta-cloud-sdk
Version: 0.1.0
Summary: A client library for accessing theta-cloud
License: MIT
Author: Tanmay Sharma
Author-email: tanmay@thetasoftware.ai
Requires-Python: >=3.9,<4.0
Classifier: License :: OSI Approved :: MIT License
Classifier: Programming Language :: Python :: 3
Classifier: Programming Language :: Python :: 3.9
Classifier: Programming Language :: Python :: 3.10
Classifier: Programming Language :: Python :: 3.11
Classifier: Programming Language :: Python :: 3.12
Classifier: Programming Language :: Python :: 3.13
Requires-Dist: attrs (>=21.3.0)
Requires-Dist: httpx (>=0.20.0,<0.28.0)
Requires-Dist: python-dateutil (>=2.8.0,<3.0.0)
Project-URL: Homepage, https://github.com/Theta-Software-Inc/theta-cloud-sdk
Project-URL: Repository, https://github.com/Theta-Software-Inc/theta-cloud-sdk
